README.md
setup.cfg
setup.py
rand_string/__init__.py
rand_string/rand_string.py
rand_string.egg-info/PKG-INFO
rand_string.egg-info/SOURCES.txt
rand_string.egg-info/dependency_links.txt
rand_string.egg-info/top_level.txt