Metadata-Version: 2.1
Name: rand-string
Version: 0.50
Summary: Generates a random string of a specified length.
Home-page: https://github.com/TheSongList/random-string
Author: TheSongList
Author-email: the@songlist.moe
License: MIT
Download-URL: https://github.com/TheSongList/random-string/archive/v0.1.tar.gz
Keywords: RANDOM,STRING,GENERATOR
Platform: UNKNOWN
Classifier: Development Status :: 3 - Alpha
Classifier: Intended Audience :: Developers
Classifier: Topic :: Software Development :: Build Tools
Classifier: License :: OSI Approved :: MIT License
Classifier: Programming Language :: Python :: 3
Classifier: Programming Language :: Python :: 3.4
Classifier: Programming Language :: Python :: 3.5
Classifier: Programming Language :: Python :: 3.6
